<?xml version="1.0" encoding="Windows-1252"?>
<spellCollection xmlns:xsi="http://www.w3.org/2001/XMLSchema-instance" xmlns:xsd="http://www.w3.org/2001/XMLSchema">
  <spells>
    <spell>
      <name>Crackle</name>
      <fearCost>5</fearCost>
      <faithCost>0</faithCost>
      <stateEffect>-1</stateEffect>
      <properties>9</properties>
      <behaviour>Strike</behaviour>
    </spell>
    <spell>
      <name>Tsunami</name>
      <fearCost>6</fearCost>
      <faithCost>0</faithCost>
      <stateEffect>-1</stateEffect>
      <properties>7</properties>
      <behaviour>Wave</behaviour>
    </spell>
    <spell>
      <name>Disease</name>
      <fearCost>10</fearCost>
      <faithCost>0</faithCost>
      <stateEffect>-1</stateEffect>
      <properties>1</properties>
      <behaviour>AOE</behaviour>
    </spell>
    <spell>
      <name>MassHeal</name>
      <fearCost>0</fearCost>
      <faithCost>10</faithCost>
      <stateEffect>1</stateEffect>
      <properties>0</properties>
      <behaviour>AOE</behaviour>
    </spell>
    <spell>
      <name>EarthQuake</name>
      <fearCost>0</fearCost>
      <faithCost>15</faithCost>
      <stateEffect>1</stateEffect>
      <properties>0</properties>
      <behaviour>Wave</behaviour>
    </spell>
  </spells>
</spellCollection>